{
  "Graph|2022-10-06T13:07:21.991Z|80828": {
    "ƒ.Graph": {
      "name": "Level",
      "active": true,
      "components": {
        "ComponentMesh": [
          {
            "ƒ.ComponentMesh": {
              "idMesh": "MeshCube|2022-10-06T13:20:58.868Z|48286",
              "pivot": {
                "translation": "[0, 0, 0]",
                "rotation": "[0, 0, 0]",
                "scaling": "[1, 1, 1]"
              },
              "Component": {
                "active": true
              }
            }
          }
        ],
        "ComponentMaterial": [
          {
            "ƒ.ComponentMaterial": {
              "sortForAlpha": false,
              "clrPrimary": "[1, 1, 1, 1]",
              "clrSecondary": "[1, 1, 1, 1]",
              "pivot": {
                "translation": "[0, 0]",
                "rotation": 0,
                "scaling": "[1, 1]"
              },
              "Component": {
                "active": true
              },
              "idMaterial": "Material|2022-10-06T13:28:25.580Z|87630"
            }
          }
        ]
      },
      "children": [],
      "idResource": "Graph|2022-10-06T13:07:21.991Z|80828",
      "type": "Graph"
    }
  },
  "MeshCube|2022-10-06T13:20:58.868Z|48286": {
    "ƒ.MeshCube": {
      "idResource": "MeshCube|2022-10-06T13:20:58.868Z|48286",
      "name": "MeshCube",
      "type": "MeshCube"
    }
  },
  "Material|2022-10-06T13:28:25.580Z|87630": {
    "ƒ.Material": {
      "name": "ShaderLit",
      "idResource": "Material|2022-10-06T13:28:25.580Z|87630",
      "shader": "ShaderLit",
      "coat": {
        "ƒ.CoatColored": {
          "color": "[1, 0, 0, 1]"
        }
      }
    }
  }
}